pychpp/__init__.py
pychpp/chpp.py
pychpp/fixtures/__init__.py
pychpp/fixtures/ht_datetime.py
pychpp/fixtures/ht_error.py
pychpp/models/__init__.py
pychpp/models/custom/__init__.py
pychpp/models/custom/base/__init__.py
pychpp/models/custom/base/ht_arena.py
pychpp/models/custom/base/ht_country.py
pychpp/models/custom/base/ht_league.py
pychpp/models/custom/base/ht_league_unit.py
pychpp/models/custom/base/ht_match.py
pychpp/models/custom/base/ht_player.py
pychpp/models/custom/base/ht_region.py
pychpp/models/custom/base/ht_team.py
pychpp/models/custom/base/ht_user.py
pychpp/models/custom/ht_arena.py
pychpp/models/custom/ht_challenge.py
pychpp/models/custom/ht_league.py
pychpp/models/custom/ht_league_unit.py
pychpp/models/custom/ht_match.py
pychpp/models/custom/ht_match_lineup.py
pychpp/models/custom/ht_matches_archive.py
pychpp/models/custom/ht_player.py
pychpp/models/custom/ht_region.py
pychpp/models/custom/ht_team.py
pychpp/models/custom/ht_transfer_history.py
pychpp/models/custom/ht_user.py
pychpp/models/custom/ht_youth_player.py
pychpp/models/custom/ht_youth_team.py
pychpp/models/ht_field.py
pychpp/models/ht_init_var.py
pychpp/models/ht_model.py
pychpp/models/ht_version.py
pychpp/models/ht_xml.py
pychpp/models/xml/__init__.py
pychpp/models/xml/achievements.py
pychpp/models/xml/alliance_details.py
pychpp/models/xml/alliances.py
pychpp/models/xml/arena_details.py
pychpp/models/xml/avatars.py
pychpp/models/xml/bookmarks.py
pychpp/models/xml/challenges.py
pychpp/models/xml/club.py
pychpp/models/xml/cup_matches.py
pychpp/models/xml/current_bids.py
pychpp/models/xml/economy.py
pychpp/models/xml/fans.py
pychpp/models/xml/hof_players.py
pychpp/models/xml/ladder_details.py
pychpp/models/xml/ladder_list.py
pychpp/models/xml/league_details.py
pychpp/models/xml/league_fixtures.py
pychpp/models/xml/league_levels.py
pychpp/models/xml/live.py
pychpp/models/xml/manager_compendium.py
pychpp/models/xml/match_details.py
pychpp/models/xml/match_lineup.py
pychpp-0.5.8.dist-info/METADATA
pychpp-0.5.8.dist-info/WHEEL
pychpp-0.5.8.dist-info/licenses/LICENSE
pychpp-0.5.8.dist-info/RECORD
