Metadata-Version: 2.4
Name: pychpp
Version: 0.5.8
Summary: framework created to use the API provided by the online game Hattrick
License: Apache-2.0
License-File: LICENSE
Author: Pierre Gobin
Author-email: p.dev@gobin.cc
Requires-Python: >=3.9,<4.0
Classifier: License :: OSI Approved :: Apache Software License
Classifier: Programming Language :: Python :: 3
Classifier: Programming Language :: Python :: 3.9
Classifier: Programming Language :: Python :: 3.10
Classifier: Programming Language :: Python :: 3.11
Classifier: Programming Language :: Python :: 3.12
Classifier: Programming Language :: Python :: 3.13
Classifier: Programming Language :: Python :: 3.14
Requires-Dist: Werkzeug (>=3.1.3,<4.0.0)
Requires-Dist: pytz (>=2025.1,<2026.0)
Requires-Dist: requests-oauthlib (>=2.0.0,<3.0.0)
Project-URL: Homepage, https://framagit.org/Pierre86/pychpp
